pyuntis/__init__.py
pyUntis-0.4.dist-info/LICENSE
pyUntis-0.4.dist-info/METADATA
pyUntis-0.4.dist-info/WHEEL
pyUntis-0.4.dist-info/top_level.txt
pyUntis-0.4.dist-info/RECORD
